README.md
setup.cfg
setup.py
sqliteplus/__init__.py
sqliteplus/sqliteplus.py
sqliteplus.egg-info/PKG-INFO
sqliteplus.egg-info/SOURCES.txt
sqliteplus.egg-info/dependency_links.txt
sqliteplus.egg-info/not-zip-safe
sqliteplus.egg-info/top_level.txt