Metadata-Version: 2.1
Name: sqliteplus
Version: 1.1.0
Summary: Прога для преобразования данных полученных из БД в словарь, где ключами выступают названия полей.
Home-page: https://github.com/prok0l/sqliteplus
Author-email: egor.kuzovkin.zr@gmail.com
